vaex/server/__init__.py
vaex/server/__main__.py
vaex/server/_version.py
vaex/server/client.py
vaex/server/dataframe.py
vaex/server/dummy.py
vaex/server/executor.py
vaex/server/fastapi.py
vaex/server/index.html
vaex/server/server.py
vaex/server/service.py
vaex/server/settings.py
vaex/server/tornado_client.py
vaex/server/tornado_server.py
vaex/server/utils.py
vaex/server/websocket.py
vaex_server-0.9.0.dist-info/LICENSE.txt
vaex_server-0.9.0.dist-info/METADATA
vaex_server-0.9.0.dist-info/WHEEL
vaex_server-0.9.0.dist-info/top_level.txt
vaex_server-0.9.0.dist-info/RECORD
